octoprint/__init__.py
octoprint/__main__.py
octoprint/_static_version.py
octoprint/_version.py
octoprint/daemon.py
octoprint/environment.py
octoprint/events.py
octoprint/timelapse.py
octoprint/users.py
octoprint/webcams.py
octoprint/access/__init__.py
octoprint/access/groups.py
octoprint/access/permissions.py
octoprint/access/users.py
octoprint/cli/__init__.py
octoprint/cli/analysis.py
octoprint/cli/client.py
octoprint/cli/common.py
octoprint/cli/config.py
octoprint/cli/dev.py
octoprint/cli/plugins.py
octoprint/cli/server.py
octoprint/cli/systeminfo.py
octoprint/cli/timelapse.py
octoprint/cli/user.py
octoprint/filemanager/__init__.py
octoprint/filemanager/analysis.py
octoprint/filemanager/destinations.py
octoprint/filemanager/storage.py
octoprint/filemanager/util.py
octoprint/logging/__init__.py
octoprint/logging/filters.py
octoprint/logging/handlers.py
octoprint/plugin/__init__.py
octoprint/plugin/core.py
octoprint/plugin/types.py
octoprint/plugins/__init__.py
octoprint/plugins/achievements/__init__.py
octoprint/plugins/achievements/achievements.py
octoprint/plugins/achievements/data.py
octoprint/plugins/achievements/static/clientjs/achievements.js
octoprint/plugins/achievements/static/css/achievements.css
octoprint/plugins/achievements/static/img/LICENSE.md
octoprint/plugins/achievements/static/img/achievement_not_found.svg
octoprint/plugins/achievements/static/img/adventurer.svg
octoprint/plugins/achievements/static/img/all_beginnings_are_hard.svg
octoprint/plugins/achievements/static/img/better_safe_than_sorry.svg
octoprint/plugins/achievements/static/img/cant_get_enough.svg
octoprint/plugins/achievements/static/img/clean_house.svg
octoprint/plugins/achievements/static/img/crossover_episode.svg
octoprint/plugins/achievements/static/img/early_bird.svg
octoprint/plugins/achievements/static/img/half_marathon.svg
octoprint/plugins/achievements/static/img/hang_in_there.svg
octoprint/plugins/achievements/static/img/happy_birthday_foosel.svg
octoprint-1.11.4.dist-info/licenses/LICENSE.txt
octoprint-1.11.4.dist-info/METADATA
octoprint-1.11.4.dist-info/WHEEL
octoprint-1.11.4.dist-info/entry_points.txt
octoprint-1.11.4.dist-info/top_level.txt
octoprint-1.11.4.dist-info/RECORD
