Metadata-Version: 2.4
Name: OctoPrint
Version: 1.11.4
Summary: The snappy web interface for your 3D printer
Home-page: https://octoprint.org
Author: Gina Häußge
Author-email: gina@octoprint.org
License: GNU Affero General Public License v3
Project-URL: Community Forum, https://community.octoprint.org
Project-URL: Bug Reports, https://github.com/OctoPrint/OctoPrint/issues
Project-URL: Source, https://github.com/OctoPrint/OctoPrint
Project-URL: Funding, https://support.octoprint.org
Keywords: 3dprinting 3dprinter 3d-printing 3d-printer octoprint
Classifier: Development Status :: 5 - Production/Stable
Classifier: Environment :: Web Environment
Classifier: Framework :: Flask
Classifier: Intended Audience :: Developers
Classifier: Intended Audience :: Education
Classifier: Intended Audience :: End Users/Desktop
Classifier: Intended Audience :: Manufacturing
Classifier: Intended Audience :: Other Audience
Classifier: Intended Audience :: Science/Research
Classifier: License :: OSI Approved :: GNU Affero General Public License v3
Classifier: Natural Language :: English
Classifier: Natural Language :: German
Classifier: Operating System :: OS Independent
Classifier: Programming Language :: Python
Classifier: Programming Language :: Python :: 3
Classifier: Programming Language :: Python :: 3.7
Classifier: Programming Language :: Python :: 3.8
Classifier: Programming Language :: Python :: 3.9
Classifier: Programming Language :: Python :: 3.10
Classifier: Programming Language :: Python :: 3.11
Classifier: Programming Language :: Python :: 3.12
Classifier: Programming Language :: Python :: 3.13
Classifier: Programming Language :: Python :: 3 :: Only
Classifier: Programming Language :: Python :: Implementation :: CPython
Classifier: Programming Language :: JavaScript
Classifier: Topic :: Printing
Requires-Python: >=3.7, <3.14
License-File: LICENSE.txt
Requires-Dist: OctoPrint-FileCheck>=2024.11.12
Requires-Dist: OctoPrint-FirmwareCheck>=2025.5.14
Requires-Dist: OctoPrint-PiSupport>=2023.10.10
Requires-Dist: argon2-cffi>=23.1.0
Requires-Dist: Babel<2.17,>=2.16; python_version >= "3.8"
Requires-Dist: cachelib<0.14,>=0.13.0; python_version >= "3.8"
Requires-Dist: Click!=8.2.0,<8.3,>=8.1.8
Requires-Dist: colorlog<7,>=6.9.0
Requires-Dist: emoji<3,>=2.14.1
Requires-Dist: feedparser<7,>=6.0.11
Requires-Dist: filetype<2,>=1.2.0
Requires-Dist: Flask-Assets<3,>=2.1.0
Requires-Dist: Flask-Babel<5,>=4.0.0; python_version >= "3.8"
Requires-Dist: Flask-Login<0.7,>=0.6.3
Requires-Dist: Flask-Limiter<3.9,>=3.8; python_version >= "3.8"
Requires-Dist: flask<3.1,>=3.0.3; python_version >= "3.8"
Requires-Dist: frozendict<3,>=2.4.6
Requires-Dist: limits<5
Requires-Dist: markdown<3.8,>=3.7; python_version >= "3.8"
Requires-Dist: markupsafe<=3.0.2; python_version <= "3.9" and platform_machine == "armv7l"
Requires-Dist: netaddr<1.4,>=1.3.0
Requires-Dist: netifaces<0.12,>=0.11.0
Requires-Dist: packaging
Requires-Dist: libpass<2,>=1.8.1; python_version >= "3.9"
Requires-Dist: passlib==1.7.4; python_version < "3.9"
Requires-Dist: pathvalidate<4,>=3.2.1
Requires-Dist: psutil<7,>=6.1.1
Requires-Dist: pydantic<3,>=2.10.6; python_version >= "3.8"
Requires-Dist: pylru<2,>=1.2.1
Requires-Dist: pyserial<4,>=3.5
Requires-Dist: pytz
Requires-Dist: PyYAML<7,>=6.0.2; python_version >= "3.8"
Requires-Dist: requests<3,>=2.32.3; python_version >= "3.8"
Requires-Dist: sarge==0.1.7.post1
Requires-Dist: semantic_version<3,>=2.10.0
Requires-Dist: sentry-sdk<3,>=2.20.0
Requires-Dist: setuptools
Requires-Dist: tornado<6.6,>=6.5; python_version >= "3.9"
Requires-Dist: tornado==6.4.2; python_version >= "3.8" and python_version < "3.9"
Requires-Dist: watchdog<5,>=4.0.2; python_version >= "3.8"
Requires-Dist: websocket-client<1.9,>=1.8.0; python_version >= "3.8"
Requires-Dist: werkzeug<3.1,>=3.0.6; python_version >= "3.8"
Requires-Dist: wrapt<1.18,>=1.17.2; python_version >= "3.8"
Requires-Dist: zeroconf<0.137,>=0.136.2; python_version >= "3.8"
Requires-Dist: zipstream-ng<2.0.0,>=1.8.0
Requires-Dist: Babel<2.15,>=2.14.0; python_version < "3.8"
Requires-Dist: cachelib<0.11,>=0.10.2; python_version < "3.8"
Requires-Dist: Flask-Babel<4,>=3.1.0; python_version < "3.8"
Requires-Dist: Flask-Limiter<3.6,>=3.5; python_version < "3.8"
Requires-Dist: flask<2.3,>=2.2.3; python_version < "3.8"
Requires-Dist: importlib-metadata>=6.7.0; python_version < "3.8"
Requires-Dist: markdown<3.5,>=3.4.4; python_version < "3.8"
Requires-Dist: pydantic==1.10.16; python_version < "3.8"
Requires-Dist: PyYAML==6.0.1; python_version < "3.8"
Requires-Dist: requests<2.32,>=2.31; python_version < "3.8"
Requires-Dist: tornado<6.3,>=6.2; python_version < "3.8"
Requires-Dist: watchdog<4,>=3.0.0; python_version < "3.8"
Requires-Dist: websocket-client==1.6.1; python_version < "3.8"
Requires-Dist: werkzeug<2.3.0,>=2.2.3; python_version < "3.8"
Requires-Dist: wrapt<1.17,>=1.16; python_version < "3.8"
Requires-Dist: zeroconf<0.132,>=0.131.0; python_version < "3.8"
Requires-Dist: blinker<1.9.0,>=1.8.0; python_version >= "3.8"
Requires-Dist: blinker<1.7.0,>=1.6.3; python_version < "3.8"
Requires-Dist: more-itertools>=10.5.0; python_version >= "3.8"
Requires-Dist: more-itertools<10,>=9.1; python_version < "3.8"
Requires-Dist: regex
Requires-Dist: unidecode
Requires-Dist: future
Requires-Dist: wheel
Requires-Dist: appdirs<2,>=1.4.4; sys_platform == "darwin"
Provides-Extra: develop
Requires-Dist: ddt; extra == "develop"
Requires-Dist: mock<6,>=5.1.0; extra == "develop"
Requires-Dist: pytest-doctest-custom<2,>=1.0.0; extra == "develop"
Requires-Dist: pytest<9,>=8.3.4; python_version >= "3.8" and extra == "develop"
Requires-Dist: pytest<8,>=7.4.4; python_version < "3.8" and extra == "develop"
Requires-Dist: ruff; extra == "develop"
Requires-Dist: pre-commit; extra == "develop"
Requires-Dist: pyinstrument; extra == "develop"
Provides-Extra: plugins
Requires-Dist: cookiecutter<3,>=2.6.0; extra == "plugins"
Provides-Extra: docs
Requires-Dist: sphinx; extra == "docs"
Requires-Dist: sphinxcontrib-httpdomain; extra == "docs"
Requires-Dist: sphinxcontrib-mermaid; extra == "docs"
Requires-Dist: sphinx_rtd_theme; extra == "docs"
Requires-Dist: readthedocs-sphinx-ext; extra == "docs"
Dynamic: author
Dynamic: author-email
Dynamic: classifier
Dynamic: description
Dynamic: description-content-type
Dynamic: home-page
Dynamic: keywords
Dynamic: license
Dynamic: license-file
Dynamic: project-url
Dynamic: provides-extra
Dynamic: requires-dist
Dynamic: requires-python
Dynamic: summary
